simple_winservice-0.1.1.dist-info/METADATA
simple_winservice-0.1.1.dist-info/WHEEL
simple_winservice-0.1.1.dist-info/licenses/LICENSE
simple_winservice/__init__.py
simple_winservice/py.typed
simple_winservice/simple_winservice.cp313-win_amd64.pyd
simple_winservice/simple_winservice.pyi
simple_winservice-0.1.1.dist-info/RECORD
