Metadata-Version: 2.4
Name: simple-winservice
Version: 0.1.1
Classifier: Development Status :: 4 - Beta
Classifier: Programming Language :: Rust
Classifier: Programming Language :: Python
License-File: LICENSE
Summary: A simple library for creating windows services and logging using windows event log
Keywords: windows,service
Author-email: Einar Omang <einar.omang@cognite.com>
License: Apache-2.0
Requires-Python: >=3.10
Project-URL: homepage, https://cognite.com
Project-URL: repository, https://github.com/cognitedata/python-windows-service
